vowel/__init__.py
vowel/cli.py
vowel/eval_types.py
vowel/evals.py
vowel/runner.py
vowel/utils.py
vowel-0.2.4.dist-info/METADATA
vowel-0.2.4.dist-info/WHEEL
vowel-0.2.4.dist-info/entry_points.txt
vowel-0.2.4.dist-info/licenses/LICENSE
vowel-0.2.4.dist-info/RECORD
