Metadata-Version: 2.4
Name: vowel
Version: 0.2.4
Summary: A modular evaluation framework for testing functions with YAML-based specifications
Project-URL: Homepage, https://github.com/fswair/vowel
Project-URL: Documentation, https://github.com/fswair/vowel#readme
Project-URL: Repository, https://github.com/fswair/vowel.git
Project-URL: Issues, https://github.com/fswair/vowel/issues
Author-email: Mert <contact@tomris.dev>
License: Apache-2.0
License-File: LICENSE
Keywords: evaluation,pydantic-evals,testing,yaml
Classifier: Development Status :: 3 - Alpha
Classifier: Intended Audience :: Developers
Classifier: License :: OSI Approved :: Apache Software License
Classifier: Programming Language :: Python :: 3
Classifier: Programming Language :: Python :: 3.10
Classifier: Programming Language :: Python :: 3.11
Classifier: Programming Language :: Python :: 3.12
Classifier: Programming Language :: Python :: 3.13
Requires-Python: >=3.10
Requires-Dist: click>=8.0.0
Requires-Dist: pydantic-evals>=0.2.0
Requires-Dist: pydantic>=2.0.0
Requires-Dist: pyyaml>=6.0.0
Provides-Extra: dev
Requires-Dist: black>=23.0.0; extra == 'dev'
Requires-Dist: pytest>=7.0.0; extra == 'dev'
Requires-Dist: ruff>=0.1.0; extra == 'dev'
